scutter/__init__.py
scutter/const.py
scutter/links.py
scutter/models.py
scutter/page.py
scutter/urls.py
scutter-0.0.0.dist-info/METADATA
scutter-0.0.0.dist-info/WHEEL
scutter-0.0.0.dist-info/top_level.txt
scutter-0.0.0.dist-info/RECORD
