Metadata-Version: 2.1
Name: scutter
Version: 0.0.0
Summary: scutter
Home-page: https://github.com/awesometoolbox/scutter
Author: UNKNOWN
Author-email: UNKNOWN
License: MIT
Keywords: scutter
Platform: UNKNOWN
Requires-Dist: requests-html
Requires-Dist: w3lib
Requires-Dist: dragnet
Requires-Dist: related
